README.md
setup.py
notifySms/__init__.py
notifySms/sendSms.py
notifySms.egg-info/PKG-INFO
notifySms.egg-info/SOURCES.txt
notifySms.egg-info/dependency_links.txt
notifySms.egg-info/requires.txt
notifySms.egg-info/top_level.txt