Metadata-Version: 2.1
Name: notifySms
Version: 1.0
Summary: Package to send sms notification to mobile
Home-page: https://github.com/kamalmansata/notfiy
Author: Kamal Mansata
Author-email: kamalmansata@gmail.com
License: UNKNOWN
Download-URL: https://github.com/kamalmansata/notfiy/archive/1.0.tar.gz
Platform: UNKNOWN
Classifier: Programming Language :: Python :: 2.7
Classifier: License :: OSI Approved :: MIT License
Classifier: Operating System :: OS Independent
